awsdjango/__init__.py
awsdjango/awsdjango.py
awsdjango-0.0.4.dist-info/METADATA
awsdjango-0.0.4.dist-info/WHEEL
awsdjango-0.0.4.dist-info/top_level.txt
awsdjango-0.0.4.dist-info/RECORD
