Metadata-Version: 2.1
Name: awsdjango
Version: 0.0.4
Summary: This package helps to create aws services which are required by django web application
Author-email: "aabhinnav@19" <applicationabhinav@gmail.com>
Requires-Python: >=3.7
Requires-Dist: boto3
